{
  "money": 200,
  "time" :
  {
    "hours" : 0,
    "minutes" : 0,
    "day" : 0
  },
  "Menu" : {},

  "market" :
  {
    "foodAvailable" :
    [
      {
        "foodName" : "Bacon",
        "foodValue" : ".50"
      },
      {
        "foodName" : "Bacon Omelette",
        "foodValue" : "6"
      },
      {
        "foodName" : "Bread",
        "foodValue" : ".50"
      },
      {
        "foodName" : "Breakfast Potatoes",
        "foodValue" : "3"
      },
      {
        "foodName" : "Cheese",
        "foodValue" : ".5"
      },
      {
        "foodName" : "Cooked Bacon",
        "foodValue" : "3"
      },
      {
        "foodName" : "Egg",
        "foodValue" : ".50"
      },
      {
        "foodName" : "Eggs and Toast",
        "foodValue" : "5"
      },
      {
        "foodName" : "Grilled Cheese",
        "foodValue" : "4"
      },
      {
        "foodName" : "Hash Browns",
        "foodValue" : "3"
      },
      {
        "foodName" : "Potato",
        "foodValue" : ".50"
      },
      {
        "foodName" : "Spinach",
        "foodValue" : ".50"
      },
      {
        "foodName" : "Spinach Omelette",
        "foodValue" : "6"
      }
    ],
    "equipmentAvailable" :
    [
      {
        "equipmentName" : "Fryer",
        "equipmentValue" : 50,
        "upkeepValue" : 2
      },
      {
        "equipmentName" : "Frying Pan",
        "equipmentValue" : 30,
        "upkeepValue" : 1.5
      },
      {
        "equipmentName" : "Oven",
        "equipmentValue" : 100,
        "upkeepValue" : 4
      },
      {
        "equipmentName" : "Toaster",
        "equipmentValue" : 25,
        "upkeepValue" : 1
      }
    ],
    "recipeAvailable" :
    [
      {
        "recipeName" : "Bacon Omlette Recipe",
        "ingredientList" : ["Bacon", "Egg"],
        "equipmentList" : ["Frying Pan"],
        "recipeValue" : 5.00,
        "timeRequired" : 15,
        "outputFood" :
        {
          "foodName" : "Bacon Omelette",
          "foodValue" : "6"
        }
      },
      {
        "recipeName" : "Breakfast Potatoes Recipe",
        "ingredientList" : ["Bacon", "Egg"],
        "equipmentList" : ["Frying Pan"],
        "recipeValue" : 3.00,
        "timeRequired" : 5,
        "outputFood" :
        {
          "foodName" : "Breakfast Potatoes",
          "foodValue" : 5
        }
      },
      {
        "recipeName" : "Cooked Bacon Recipe",
        "ingredientList" : ["Bacon"],
        "equipmentList" : ["Frying Pan"],
        "recipeValue" : 3.00,
        "timeRequired" : 5,
        "outputFood" :
        {
          "foodName" : "Cooked Bacon",
          "foodValue" : 5
        }
      },
      {
        "recipeName" : "Eggs and Toast Recipe",
        "ingredientList" : ["Egg", "Bread"],
        "equipmentList" : ["Frying Pan","Toaster"],
        "recipeValue" : 5.00,
        "timeRequired" : 12,
        "outputFood" :
        {
          "foodName" : "Eggs and Toast",
          "foodValue" : 5
        }
      },
      {
        "recipeName" : "Grilled Cheese Recipe",
        "ingredientList" : ["Cheese", "Bread"],
        "equipmentList" : ["Frying Pan"],
        "recipeValue" : 4.00,
        "timeRequired" : 10,
        "outputFood" :
        {
          "foodName" : "Grilled Cheese",
          "foodValue" : 4
        }
      },
      {
        "recipeName" : "Hash Browns Recipe",
        "ingredientList" : ["Potato"],
        "equipmentList" : ["Fryer"],
        "recipeValue" : 3.00,
        "timeRequired" : 5,
        "outputFood" :
        {
          "foodName" : "Hash Browns",
          "foodValue" : 3
        }
      },
      {
        "recipeName" : "Spinach Omeltte Recipe",
        "ingredientList" : ["Egg", "Spinach"],
        "equipmentList" : ["Frying Pan"],
        "recipeValue" : 5.00,
        "timeRequired" : 15,
        "outputFood" :
        {
          "foodName" : "Spinach Omeltte",
          "foodValue" : 3
        }
      }
    ]
  }
}